reactive/core/__init__.py
reactive_core-0.0.1.dist-info/METADATA
reactive_core-0.0.1.dist-info/WHEEL
reactive_core-0.0.1.dist-info/RECORD
