Metadata-Version: 2.1
Name: reactive-core
Version: 0.0.1
Project-URL: Documentation, https://github.com/reactive-python/reactive
Project-URL: Issues, https://github.com/reactive-python/reactive/labels/reactive-core
Project-URL: Source, https://github.com/reactive-python/reactive/tree/main/packages/reactive-core
Author-email: rmorshea <ryan.morshead@gmail.com>
Classifier: Development Status :: 4 - Beta
Classifier: Programming Language :: Python
Classifier: Programming Language :: Python :: 3.7
Classifier: Programming Language :: Python :: 3.8
Classifier: Programming Language :: Python :: 3.9
Classifier: Programming Language :: Python :: 3.10
Classifier: Programming Language :: Python :: 3.11
Classifier: Programming Language :: Python :: Implementation :: CPython
Classifier: Programming Language :: Python :: Implementation :: PyPy
Requires-Python: >=3.7
